{
  "publicPath": "https://d1mecfk3si22ar.cloudfront.net/",
  "all": [
    "0.89259ab69ef620125669.js",
    "1.739bb8debbf8ddbe13d6.js",
    "app.f136e52e753dec2fb0b1.js",
    "vendor.7e77a990aab592e8b244.js",
    "manifest.b177aa409d52fef95669.js",
    "common.f136e52e753dec2fb0b1.css"
  ],
  "initial": [
    "manifest.b177aa409d52fef95669.js",
    "vendor.7e77a990aab592e8b244.js",
    "app.f136e52e753dec2fb0b1.js"
  ],
  "async": [
    "0.89259ab69ef620125669.js",
    "1.739bb8debbf8ddbe13d6.js"
  ],
  "modules": {
    "19475234": [
      3
    ],
    "83887dda": [
      3
    ],
    "8f5c43b8": [
      2,
      5
    ],
    "0fa30134": [
      3
    ],
    "de2c6902": [
      3
    ],
    "29de117e": [
      3
    ],
    "636f9763": [
      2,
      5
    ],
    "6ac14f5d": [
      2,
      5
    ],
    "4c3b93d2": [
      2,
      5
    ],
    "70bd6eee": [
      3
    ],
    "47aacc72": [
      2,
      5
    ],
    "3828f780": [
      2,
      5
    ],
    "433c4cb8": [
      3
    ],
    "1665e8b5": [
      2,
      5
    ],
    "426fc0e8": [
      2,
      5
    ],
    "2db3e10a": [
      2,
      5
    ],
    "0eeb1f5e": [
      2,
      5
    ],
    "00177a88": [
      3
    ],
    "bac254c0": [
      3
    ],
    "7325ff61": [
      2,
      5
    ],
    "3c0add50": [
      2,
      5
    ],
    "4e124104": [
      2,
      5
    ],
    "1c9888b8": [
      2,
      5
    ],
    "d9a2cda0": [
      3
    ],
    "d2b219c8": [
      3
    ],
    "4514aed4": [
      1
    ],
    "352988c4": [
      0
    ],
    "1e340cf7": [
      1
    ],
    "8ec299dc": [
      1
    ],
    "7fe9f856": [
      0
    ],
    "723003f5": [
      0
    ],
    "7ff5ef01": [
      0
    ],
    "47811a74": [
      0
    ]
  }
}